hyp3lib/.gitignore
hyp3lib/__init__.py
hyp3lib/asf_geometry.py
hyp3lib/asf_time_series.py
hyp3lib/aws.py
hyp3lib/dem.py
hyp3lib/exceptions.py
hyp3lib/execute.py
hyp3lib/fetch.py
hyp3lib/get_orb.py
hyp3lib/image.py
hyp3lib/resample_geotiff.py
hyp3lib/rtc2color.py
hyp3lib/scene.py
hyp3lib/util.py
hyp3lib-4.0.1.data/scripts/GC_map_mod
hyp3lib-4.0.1.dist-info/licenses/LICENSE
hyp3lib-4.0.1.dist-info/METADATA
hyp3lib-4.0.1.dist-info/WHEEL
hyp3lib-4.0.1.dist-info/entry_points.txt
hyp3lib-4.0.1.dist-info/top_level.txt
hyp3lib-4.0.1.dist-info/RECORD
