Metadata-Version: 2.4
Name: hyp3lib
Version: 4.0.1
Summary: Common library for HyP3 plugins
Author-email: ASF APD/Tools Team <UAF-asf-apd@alaska.edu>
License: BSD-3-Clause
Classifier: Development Status :: 5 - Production/Stable
Classifier: Intended Audience :: Science/Research
Classifier: License :: OSI Approved :: BSD License
Classifier: Natural Language :: English
Classifier: Programming Language :: Python :: 3
Classifier: Programming Language :: Python :: 3.10
Classifier: Programming Language :: Python :: 3.11
Classifier: Programming Language :: Python :: 3.12
Classifier: Programming Language :: Python :: 3.13
Classifier: Topic :: Software Development :: Libraries
Requires-Python: >=3.10
License-File: LICENSE
Requires-Dist: boto3>=1.36.0
Requires-Dist: gdal<3.11.1
Requires-Dist: lxml
Requires-Dist: netCDF4
Requires-Dist: numpy
Requires-Dist: pillow
Requires-Dist: requests
Requires-Dist: scipy
Requires-Dist: statsmodels
Requires-Dist: urllib3
Provides-Extra: develop
Requires-Dist: botocore; extra == "develop"
Requires-Dist: ruff; extra == "develop"
Requires-Dist: pytest; extra == "develop"
Requires-Dist: pytest-cov; extra == "develop"
Requires-Dist: pytest-console-scripts; extra == "develop"
Requires-Dist: responses; extra == "develop"
Dynamic: license-file
